Metadata-Version: 1.0
Name: sw-billing
Version: 0.0.1
Summary: Soft-Way billing
Home-page: https://gitlab.soft-way.biz/soft-way/billing
Author: nick1994209
Author-email: nick1994209@gmail.com
License: MIT
Platform: UNKNOWN
